plasticwrap/__init__.py
plasticwrap/methods.json
plasticwrap/plasticwrap.py
plasticwrap-0.1.1.dist-info/METADATA
plasticwrap-0.1.1.dist-info/WHEEL
plasticwrap-0.1.1.dist-info/RECORD
